bmb/__init__.py
bmb/app.py
bmb/cli.py
bmb/database.py
bmb/models_loader.py
bmb/config/__init__.py
bmb/config/app_config.py
bmb/config/bmdb_config.py
bmb/middleware/__init__.py
bmb/middleware/error_handlers.py
bmb/middleware/logging.py
bmb/project_template/__init__.py
bmb/project_template/app.py
bmb/project_template/database.py
bmb/project_template/models_loader.py
bmb/project_template/config/__init__.py
bmb/project_template/config/app_config.py
bmb/project_template/config/bmdb_config.py
bmb/project_template/middleware/__init__.py
bmb/project_template/middleware/error_handlers.py
bmb/project_template/middleware/logging.py
bmb/project_template/routes/__init__.py
bmb/project_template/routes/auth.py
bmb/project_template/routes/health.py
bmb/project_template/routes/users.py
bmb/project_template/utils/__init__.py
bmb/project_template/utils/jwt_utils.py
bmb/project_template/utils/responses.py
bmb/project_template/utils/validators.py
bmb/routes/__init__.py
bmb/routes/auth.py
bmb/routes/health.py
bmb/routes/users.py
bmb/utils/__init__.py
bmb/utils/jwt_utils.py
bmb/utils/responses.py
bmb/utils/validators.py
bmdb/models/generated/__init__.py
bmdb/models/generated/migrate.py
bmdb/models/generated/models.py
tests/conftest.py
tests/test_auth.py
tests/test_health.py
tests/test_models_loader.py
tests/test_users.py
bmb-1.0.5.dist-info/METADATA
bmb-1.0.5.dist-info/WHEEL
bmb-1.0.5.dist-info/entry_points.txt
bmb-1.0.5.dist-info/top_level.txt
bmb-1.0.5.dist-info/RECORD
