Metadata-Version: 2.4
Name: bmb
Version: 1.0.5
Summary: BMB - Backend Framework utilisant BMDB ORM
Home-page: https://github.com/BM-Framework/bmb
Author: Marouan Bouchettoy
Author-email: Marouan Bouchettoy <marouanbouchettoy@gmail.com>
License: MIT
Project-URL: Homepage, https://github.com/BM-Framework/bmb
Project-URL: Repository, https://github.com/BM-Framework/bmb
Project-URL: Issues, https://github.com/BM-Framework/bmb/issues
Keywords: web,framework,backend,orm,flask
Classifier: Development Status :: 4 - Beta
Classifier: Intended Audience :: Developers
Classifier: Topic :: Software Development :: Libraries :: Application Frameworks
Classifier: License :: OSI Approved :: MIT License
Classifier: Programming Language :: Python :: 3
Classifier: Programming Language :: Python :: 3.8
Classifier: Programming Language :: Python :: 3.9
Classifier: Programming Language :: Python :: 3.10
Classifier: Programming Language :: Python :: 3.11
Classifier: Programming Language :: Python :: 3.12
Requires-Python: >=3.8
Requires-Dist: Flask>=3.1.2
Requires-Dist: flask-cors>=6.0.2
Requires-Dist: PyJWT>=2.10.1
Requires-Dist: python-dotenv>=1.2.1
Requires-Dist: Werkzeug>=3.1.5
Requires-Dist: bmdb>=1.2.0
Provides-Extra: dev
Requires-Dist: pytest>=9.0.2; extra == "dev"
Requires-Dist: pytest-cov>=4.1.0; extra == "dev"
Requires-Dist: black>=23.0.0; extra == "dev"
Requires-Dist: flake8>=6.0.0; extra == "dev"
Requires-Dist: mypy>=1.5.0; extra == "dev"
Provides-Extra: postgresql
Requires-Dist: psycopg2-binary>=2.9.0; extra == "postgresql"
Provides-Extra: mysql
Requires-Dist: pymysql>=1.1.0; extra == "mysql"
Dynamic: author
Dynamic: home-page
Dynamic: requires-python
